faucetpay/__init__.py
faucetpay/faucetpay.py
faucetpay-1.1.dist-info/METADATA
faucetpay-1.1.dist-info/WHEEL
faucetpay-1.1.dist-info/top_level.txt
faucetpay-1.1.dist-info/RECORD
