Metadata-Version: 2.1
Name: faucetpay
Version: 1.1
Summary: Unofficial Python Library For Faucetpay API
Author: vboxvm512
Author-email: vboxvm512@gmail.com
License: MIT
Platform: any
Requires-Dist: requests
Requires-Dist: urllib3
